tuxsuite/__init__.py
tuxsuite/__main__.py
tuxsuite/build.py
tuxsuite/config.py
tuxsuite/download.py
tuxsuite/exceptions.py
tuxsuite/gitutils.py
tuxsuite/local_plan.py
tuxsuite/requests.py
tuxsuite/schema.py
tuxsuite/utils.py
tuxsuite/xdg.py
tuxsuite/cli/__init__.py
tuxsuite/cli/bake.py
tuxsuite/cli/build.py
tuxsuite/cli/colors.py
tuxsuite/cli/common.py
tuxsuite/cli/config.py
tuxsuite/cli/group.py
tuxsuite/cli/icons.py
tuxsuite/cli/keys.py
tuxsuite/cli/models.py
tuxsuite/cli/plan.py
tuxsuite/cli/project.py
tuxsuite/cli/requests.py
tuxsuite/cli/results.py
tuxsuite/cli/test.py
tuxsuite/cli/trigger.py
tuxsuite/cli/utils.py
tuxsuite/cli/version.py
tuxsuite/cli/yaml.py
tuxsuite-1.44.4.dist-info/entry_points.txt
tuxsuite-1.44.4.dist-info/licenses/LICENSE
tuxsuite-1.44.4.dist-info/WHEEL
tuxsuite-1.44.4.dist-info/METADATA
tuxsuite-1.44.4.dist-info/RECORD
