Metadata-Version: 2.4
Name: tuxsuite
Version: 1.44.4
Summary: This is the tuxsuite module.
Home-page: https://www.tuxsuite.com/
Author: Senthil Kumaran
Author-email: senthil.kumaran@linaro.org
Requires-Python: >=3.7
Classifier: License :: OSI Approved :: MIT License
License-File: LICENSE
Requires-Dist: attrs
Requires-Dist: requests
Requires-Dist: pyyaml
Requires-Dist: voluptuous
Requires-Dist: b4
Requires-Dist: tuxmake
Requires-Dist: tuxrun
